README.txt
setup.py
protein_package/__init__.py
protein_package/protein_class.py
residue_counting.egg-info/PKG-INFO
residue_counting.egg-info/SOURCES.txt
residue_counting.egg-info/dependency_links.txt
residue_counting.egg-info/top_level.txt