Metadata-Version: 1.0
Name: residue-counting
Version: 0.1
Summary: cool stuff
Home-page: http://example.com
Author: Example
Author-email: Example@gmail.com
License: Example
Platform: UNKNOWN
